robotics_transformer/.git
robotics_transformer/.gitattributes
robotics_transformer/.gitignore
robotics_transformer/.pylintrc
robotics_transformer/CONTRIBUTING.md
robotics_transformer/LICENSE
robotics_transformer/README.md
robotics_transformer/__init__.py
robotics_transformer/configs/transformer_mixin.gin
robotics_transformer/film_efficientnet/__init__.py
robotics_transformer/film_efficientnet/efficientnet_checkpoints/efficientnetb3.h5
robotics_transformer/film_efficientnet/efficientnet_checkpoints/efficientnetb3_notop.h5
robotics_transformer/film_efficientnet/efficientnet_checkpoints/imagenet_classes.json
robotics_transformer/film_efficientnet/film_conditioning_layer.py
robotics_transformer/film_efficientnet/film_conditioning_layer_test.py
robotics_transformer/film_efficientnet/film_efficientnet_encoder.py
robotics_transformer/film_efficientnet/film_efficientnet_encoder_test.py
robotics_transformer/film_efficientnet/preprocessors.py
robotics_transformer/film_efficientnet/preprocessors_test.py
robotics_transformer/film_efficientnet/pretrained_efficientnet_encoder.py
robotics_transformer/film_efficientnet/pretrained_efficientnet_encoder_test.py
robotics_transformer/requirements.txt
robotics_transformer/sequence_agent.py
robotics_transformer/sequence_agent_test.py
robotics_transformer/sequence_agent_test_set_up.py
robotics_transformer/tokenizers/__init__.py
robotics_transformer/tokenizers/action_tokenizer.py
robotics_transformer/tokenizers/action_tokenizer_test.py
robotics_transformer/tokenizers/image_tokenizer.py
robotics_transformer/tokenizers/image_tokenizer_test.py
robotics_transformer/tokenizers/token_learner.py
robotics_transformer/tokenizers/token_learner_test.py
robotics_transformer/trained_checkpoints/rt1main/assets/metadata.textproto
robotics_transformer/trained_checkpoints/rt1main/checkpoint
robotics_transformer/trained_checkpoints/rt1main/ckpt-424760.index
robotics_transformer/trained_checkpoints/rt1main/fingerprint.pb
robotics_transformer-0.1.1.dist-info/LICENSE
robotics_transformer-0.1.1.dist-info/METADATA
robotics_transformer-0.1.1.dist-info/WHEEL
robotics_transformer-0.1.1.dist-info/RECORD
